{
  "version": 1,
  "width": 80,
  "height": 24,
  "duration": 135.074698,
  "command": "/bin/bash",
  "title": "",
  "env": {
    "TERM": "xterm-256color",
    "SHELL": "/bin/bash"
  },
  "stdout": [
    [
      0.200747,
      "\u001b[?1034h[laks@ webminal.org]$ "
    ],
    [
      1.271588,
      "#"
    ],
    [
      0.187124,
      " "
    ],
    [
      0.775960,
      "H"
    ],
    [
      0.332420,
      "o"
    ],
    [
      0.108900,
      "w"
    ],
    [
      0.109250,
      " "
    ],
    [
      0.142896,
      "t"
    ],
    [
      0.042104,
      "o"
    ],
    [
      0.109637,
      " "
    ],
    [
      0.142868,
      "e"
    ],
    [
      0.233372,
      "x"
    ],
    [
      0.307255,
      "t"
    ],
    [
      0.493380,
      "r"
    ],
    [
      0.191582,
      "a"
    ],
    [
      0.232178,
      "c"
    ],
    [
      0.394612,
      "t"
    ],
    [
      0.107761,
      " "
    ],
    [
      0.190086,
      "f"
    ],
    [
      0.256413,
      "i"
    ],
    [
      0.061167,
      "l"
    ],
    [
      0.150941,
      "e"
    ],
    [
      0.209455,
      "n"
    ],
    [
      0.061103,
      "a"
    ],
    [
      0.185118,
      "m"
    ],
    [
      0.102024,
      "e"
    ],
    [
      0.100135,
      " "
    ],
    [
      0.230558,
      "f"
    ],
    [
      0.071121,
      "r"
    ],
    [
      0.140767,
      "o"
    ],
    [
      0.066905,
      "m"
    ],
    [
      0.488124,
      " "
    ],
    [
      0.732747,
      "p"
    ],
    [
      0.101542,
      "a"
    ],
    [
      0.221421,
      "t"
    ],
    [
      0.114348,
      "h"
    ],
    [
      0.538855,
      "?"
    ],
    [
      0.761274,
      "\r\n[laks@ webminal.org]$ "
    ],
    [
      0.451550,
      "#"
    ],
    [
      0.150403,
      " "
    ],
    [
      0.596386,
      "L"
    ],
    [
      0.137059,
      "e"
    ],
    [
      0.131819,
      "t"
    ],
    [
      0.187802,
      "s"
    ],
    [
      0.099327,
      " "
    ],
    [
      0.228234,
      "s"
    ],
    [
      0.087619,
      "a"
    ],
    [
      0.302936,
      "y"
    ],
    [
      0.193733,
      " "
    ],
    [
      0.164080,
      "w"
    ],
    [
      0.078641,
      "e"
    ],
    [
      0.095401,
      " "
    ],
    [
      0.191986,
      "h"
    ],
    [
      0.061337,
      "a"
    ],
    [
      0.240484,
      "v"
    ],
    [
      0.154106,
      "e"
    ],
    [
      0.423165,
      " "
    ],
    [
      0.647947,
      "p"
    ],
    [
      0.104968,
      "a"
    ],
    [
      0.233779,
      "t"
    ],
    [
      0.128015,
      "h"
    ],
    [
      0.359083,
      " "
    ],
    [
      0.349035,
      "l"
    ],
    [
      0.186579,
      "i"
    ],
    [
      0.176168,
      "k"
    ],
    [
      0.074389,
      "e"
    ],
    [
      0.099771,
      " "
    ],
    [
      0.495604,
      "\r\n[laks@ webminal.org]$ "
    ],
    [
      0.352731,
      "#"
    ],
    [
      0.409893,
      " "
    ],
    [
      0.259290,
      "/"
    ],
    [
      0.187307,
      "h"
    ],
    [
      0.174128,
      "o"
    ],
    [
      0.061932,
      "m"
    ],
    [
      0.144881,
      "e"
    ],
    [
      0.283820,
      "/"
    ],
    [
      1.344996,
      "l"
    ],
    [
      0.093416,
      "a"
    ],
    [
      0.114144,
      "k"
    ],
    [
      0.110166,
      "s"
    ],
    [
      0.264051,
      "/"
    ],
    [
      1.716280,
      "s"
    ],
    [
      0.159233,
      "o"
    ],
    [
      0.047024,
      "m"
    ],
    [
      0.143875,
      "e"
    ],
    [
      0.233930,
      "/"
    ],
    [
      0.196636,
      "d"
    ],
    [
      0.185013,
      "i"
    ],
    [
      0.106653,
      "r"
    ],
    [
      0.461071,
      "/"
    ],
    [
      0.510292,
      "f"
    ],
    [
      0.164229,
      "i"
    ],
    [
      0.071289,
      "l"
    ],
    [
      0.141436,
      "e"
    ],
    [
      0.200360,
      "."
    ],
    [
      0.163326,
      "t"
    ],
    [
      0.273810,
      "x"
    ],
    [
      0.300220,
      "t"
    ],
    [
      0.405323,
      "\r\n[laks@ webminal.org]$ "
    ],
    [
      0.357566,
      "#"
    ],
    [
      0.118474,
      " "
    ],
    [
      0.301667,
      "w"
    ],
    [
      0.056727,
      "e"
    ],
    [
      0.160193,
      " "
    ],
    [
      0.333279,
      "w"
    ],
    [
      0.098665,
      "a"
    ],
    [
      0.262107,
      "n"
    ],
    [
      0.139374,
      "t"
    ],
    [
      0.122107,
      " "
    ],
    [
      0.258241,
      "o"
    ],
    [
      0.169430,
      "n"
    ],
    [
      0.194887,
      "l"
    ],
    [
      0.155389,
      "y"
    ],
    [
      0.188634,
      " "
    ],
    [
      1.265021,
      "f"
    ],
    [
      0.199978,
      "i"
    ],
    [
      0.085049,
      "l"
    ],
    [
      0.133191,
      "e"
    ],
    [
      0.212914,
      "."
    ],
    [
      0.145950,
      "t"
    ],
    [
      0.310089,
      "x"
    ],
    [
      0.336558,
      "t"
    ],
    [
      0.411757,
      " "
    ],
    [
      2.368758,
      "."
    ],
    [
      0.151894,
      "."
    ],
    [
      0.509685,
      " "
    ],
    [
      0.076590,
      "h"
    ],
    [
      0.174131,
      "o"
    ],
    [
      0.395224,
      "w"
    ],
    [
      0.158943,
      " "
    ],
    [
      0.145804,
      "t"
    ],
    [
      0.094730,
      "o"
    ],
    [
      0.084148,
      " "
    ],
    [
      0.211032,
      "g"
    ],
    [
      0.109676,
      "e"
    ],
    [
      0.471347,
      "t"
    ],
    [
      0.215403,
      " "
    ],
    [
      0.126284,
      "t"
    ],
    [
      0.192601,
      "h"
    ],
    [
      0.048026,
      "i"
    ],
    [
      0.130320,
      "s"
    ],
    [
      0.384308,
      "?"
    ],
    [
      1.430494,
      "\r\n[laks@ webminal.org]$ "
    ],
    [
      1.845697,
      "#"
    ],
    [
      0.867941,
      " "
    ],
    [
      0.496853,
      "i"
    ],
    [
      0.117452,
      "t"
    ],
    [
      0.208264,
      "s"
    ],
    [
      0.098795,
      " "
    ],
    [
      0.132275,
      "s"
    ],
    [
      0.157870,
      "i"
    ],
    [
      0.252357,
      "m"
    ],
    [
      0.229797,
      "p"
    ],
    [
      0.051442,
      "l"
    ],
    [
      0.598282,
      "e"
    ],
    [
      0.127112,
      " "
    ],
    [
      0.117615,
      "w"
    ],
    [
      0.122926,
      "i"
    ],
    [
      0.130549,
      "t"
    ],
    [
      0.161108,
      "h"
    ],
    [
      0.165056,
      " "
    ],
    [
      1.258401,
      "b"
    ],
    [
      0.088949,
      "a"
    ],
    [
      0.209804,
      "s"
    ],
    [
      0.093199,
      "h"
    ],
    [
      0.506695,
      "."
    ],
    [
      0.712791,
      " "
    ],
    [
      0.268009,
      "W"
    ],
    [
      0.164233,
      "e"
    ],
    [
      0.106028,
      " "
    ],
    [
      0.246084,
      "h"
    ],
    [
      0.068973,
      "a"
    ],
    [
      0.240148,
      "v"
    ],
    [
      0.187571,
      "e"
    ],
    [
      0.587729,
      "\r\n[laks@ webminal.org]$ "
    ],
    [
      0.534660,
      "#"
    ],
    [
      0.074440,
      " "
    ],
    [
      0.786844,
      "b"
    ],
    [
      0.138340,
      "a"
    ],
    [
      0.233721,
      "s"
    ],
    [
      0.093639,
      "e"
    ],
    [
      0.122850,
      "n"
    ],
    [
      0.838946,
      "a"
    ],
    [
      0.470600,
      "m"
    ],
    [
      0.120707,
      "e"
    ],
    [
      0.161755,
      " "
    ],
    [
      0.204462,
      "c"
    ],
    [
      0.076630,
      "o"
    ],
    [
      0.194697,
      "m"
    ],
    [
      0.167195,
      "m"
    ],
    [
      0.061874,
      "a"
    ],
    [
      0.145642,
      "n"
    ],
    [
      0.100528,
      "d"
    ],
    [
      0.337770,
      "."
    ],
    [
      1.242047,
      "\r\n[laks@ webminal.org]$ "
    ],
    [
      0.827928,
      "b"
    ],
    [
      0.130247,
      "a"
    ],
    [
      0.687927,
      "s"
    ],
    [
      0.126701,
      "e"
    ],
    [
      0.829035,
      "n"
    ],
    [
      0.076131,
      "a"
    ],
    [
      0.164609,
      "m"
    ],
    [
      0.126794,
      "e"
    ],
    [
      0.146310,
      " "
    ],
    [
      1.178415,
      "/"
    ],
    [
      0.241157,
      "h"
    ],
    [
      0.107492,
      "o"
    ],
    [
      0.061510,
      "m"
    ],
    [
      0.136624,
      "e"
    ],
    [
      0.207052,
      "/"
    ],
    [
      0.238248,
      "l"
    ],
    [
      0.061048,
      "a"
    ],
    [
      0.183156,
      "k"
    ],
    [
      0.061891,
      "s"
    ],
    [
      0.206730,
      "/"
    ],
    [
      0.186860,
      "s"
    ],
    [
      0.167071,
      "o"
    ],
    [
      0.076374,
      "m"
    ],
    [
      0.125996,
      "e"
    ],
    [
      0.266368,
      "/"
    ],
    [
      0.279352,
      "d"
    ],
    [
      0.144387,
      "i"
    ],
    [
      0.134756,
      "r"
    ],
    [
      0.254794,
      "/"
    ],
    [
      0.234734,
      "f"
    ],
    [
      0.197563,
      "i"
    ],
    [
      0.079737,
      "l"
    ],
    [
      0.117171,
      "e"
    ],
    [
      0.382212,
      "."
    ],
    [
      0.130878,
      "t"
    ],
    [
      0.275007,
      "x"
    ],
    [
      0.245395,
      "t"
    ],
    [
      0.516843,
      "\r\n"
    ],
    [
      0.001607,
      "file.txt\r\n"
    ],
    [
      0.001352,
      "[laks@ webminal.org]$ "
    ],
    [
      2.309848,
      "#"
    ],
    [
      0.150729,
      " "
    ],
    [
      0.609083,
      "s"
    ],
    [
      0.218137,
      "e"
    ],
    [
      0.163694,
      "e"
    ],
    [
      0.541580,
      " "
    ],
    [
      0.278372,
      "?"
    ],
    [
      0.169508,
      " "
    ],
    [
      0.395370,
      "w"
    ],
    [
      0.117595,
      "e"
    ],
    [
      0.099087,
      " "
    ],
    [
      0.225962,
      "g"
    ],
    [
      0.104769,
      "o"
    ],
    [
      0.151067,
      "t"
    ],
    [
      0.168672,
      "t"
    ],
    [
      0.167006,
      "h"
    ],
    [
      0.377486,
      "\u0008\u001b[K"
    ],
    [
      0.154809,
      "\u0008\u001b[K"
    ],
    [
      0.140951,
      " "
    ],
    [
      0.070248,
      "t"
    ],
    [
      0.256338,
      "h"
    ],
    [
      0.117224,
      "e"
    ],
    [
      0.104603,
      " "
    ],
    [
      0.207337,
      "o"
    ],
    [
      0.266583,
      "t"
    ],
    [
      0.425944,
      "\u0008\u001b[K"
    ],
    [
      0.319831,
      "u"
    ],
    [
      0.504080,
      "t"
    ],
    [
      0.482536,
      "p"
    ],
    [
      0.279749,
      "u"
    ],
    [
      0.129992,
      "t"
    ],
    [
      0.448826,
      "!"
    ],
    [
      0.724573,
      "\r\n[laks@ webminal.org]$ "
    ],
    [
      2.307483,
      "#"
    ],
    [
      0.266776,
      " "
    ],
    [
      0.811740,
      "L"
    ],
    [
      0.235345,
      "e"
    ],
    [
      0.233624,
      "t"
    ],
    [
      0.117746,
      " "
    ],
    [
      0.409326,
      "s"
    ],
    [
      0.094585,
      "a"
    ],
    [
      0.305010,
      "y"
    ],
    [
      0.297606,
      " "
    ],
    [
      0.173406,
      "w"
    ],
    [
      0.113493,
      "e"
    ],
    [
      0.066415,
      " "
    ],
    [
      0.269885,
      "w"
    ],
    [
      0.114309,
      "a"
    ],
    [
      0.149150,
      "n"
    ],
    [
      0.174075,
      "t"
    ],
    [
      0.182143,
      " "
    ],
    [
      0.204084,
      "o"
    ],
    [
      0.148614,
      "n"
    ],
    [
      0.238109,
      "l"
    ],
    [
      0.106396,
      "y"
    ],
    [
      0.216552,
      " "
    ],
    [
      2.461363,
      "d"
    ],
    [
      0.131281,
      "i"
    ],
    [
      0.116881,
      "r"
    ],
    [
      0.602326,
      "p"
    ],
    [
      0.094775,
      "a"
    ],
    [
      0.231329,
      "t"
    ],
    [
      0.084912,
      "h"
    ],
    [
      0.258363,
      " "
    ],
    [
      1.147956,
      "\r\n[laks@ webminal.org]$ "
    ],
    [
      0.350811,
      "#"
    ],
    [
      0.093928,
      " "
    ],
    [
      0.373809,
      "n"
    ],
    [
      0.185280,
      "o"
    ],
    [
      0.118788,
      "t"
    ],
    [
      0.080590,
      " "
    ],
    [
      0.317456,
      "i"
    ],
    [
      0.098529,
      "l"
    ],
    [
      0.299244,
      "\u0008\u001b[K"
    ],
    [
      0.149858,
      "\u0008\u001b[K"
    ],
    [
      0.202599,
      "f"
    ],
    [
      0.177029,
      "i"
    ],
    [
      0.341751,
      "l"
    ],
    [
      0.406677,
      "e"
    ],
    [
      0.132705,
      "n"
    ],
    [
      0.145811,
      "a"
    ],
    [
      0.117838,
      "m"
    ],
    [
      0.153464,
      "e"
    ],
    [
      0.644765,
      "\r\n[laks@ webminal.org]$ "
    ],
    [
      0.543305,
      "#"
    ],
    [
      0.668911,
      " "
    ],
    [
      1.484867,
      "i"
    ],
    [
      0.285235,
      "."
    ],
    [
      0.110408,
      "e"
    ],
    [
      0.089195,
      " "
    ],
    [
      0.214631,
      "w"
    ],
    [
      0.103235,
      "e"
    ],
    [
      0.061087,
      " "
    ],
    [
      0.783640,
      "w"
    ],
    [
      0.074354,
      "a"
    ],
    [
      0.199766,
      "n"
    ],
    [
      0.148637,
      "t"
    ],
    [
      0.089681,
      " "
    ],
    [
      0.232622,
      "/"
    ],
    [
      0.206443,
      "h"
    ],
    [
      0.094387,
      "o"
    ],
    [
      0.071316,
      "m"
    ],
    [
      0.151330,
      "e"
    ],
    [
      0.177714,
      "/"
    ],
    [
      0.243292,
      "l"
    ],
    [
      0.104565,
      "a"
    ],
    [
      0.128126,
      "k"
    ],
    [
      0.089644,
      "s"
    ],
    [
      0.169175,
      "/"
    ],
    [
      0.261400,
      "s"
    ],
    [
      0.103197,
      "o"
    ],
    [
      0.081139,
      "m"
    ],
    [
      0.118294,
      "e"
    ],
    [
      0.310129,
      "/"
    ],
    [
      0.148317,
      "d"
    ],
    [
      0.141947,
      "i"
    ],
    [
      0.114768,
      "r"
    ],
    [
      1.240623,
      "\r\n[laks@ webminal.org]$ "
    ],
    [
      1.729560,
      "W"
    ],
    [
      0.466550,
      "\u0008\u001b[K"
    ],
    [
      0.323413,
      "#"
    ],
    [
      0.155963,
      " "
    ],
    [
      0.344538,
      "f"
    ],
    [
      0.083997,
      "o"
    ],
    [
      0.110296,
      "r"
    ],
    [
      0.080294,
      " "
    ],
    [
      0.385906,
      "t"
    ],
    [
      0.137048,
      "h"
    ],
    [
      0.056563,
      "i"
    ],
    [
      0.099253,
      "s"
    ],
    [
      0.122384,
      " "
    ],
    [
      0.184325,
      "w"
    ],
    [
      0.102355,
      "e"
    ],
    [
      0.095088,
      " "
    ],
    [
      0.211220,
      "c"
    ],
    [
      0.037643,
      "a"
    ],
    [
      0.125545,
      "n"
    ],
    [
      0.079885,
      " "
    ],
    [
      0.639871,
      "u"
    ],
    [
      0.074183,
      "s"
    ],
    [
      0.084695,
      "e"
    ],
    [
      0.146785,
      " "
    ],
    [
      0.500306,
      "c"
    ],
    [
      0.024135,
      "o"
    ],
    [
      0.340889,
      "m"
    ],
    [
      0.154252,
      "m"
    ],
    [
      0.180731,
      "a"
    ],
    [
      0.112576,
      "n"
    ],
    [
      0.166384,
      "d"
    ],
    [
      0.123458,
      " "
    ],
    [
      0.202406,
      "c"
    ],
    [
      0.061498,
      "a"
    ],
    [
      0.084530,
      "l"
    ],
    [
      0.133107,
      "l"
    ],
    [
      0.051180,
      "e"
    ],
    [
      0.195382,
      "d"
    ],
    [
      0.505728,
      "\r\n"
    ],
    [
      0.000788,
      "[laks@ webminal.org]$ "
    ],
    [
      0.320702,
      "#"
    ],
    [
      0.103742,
      " "
    ],
    [
      0.525120,
      "d"
    ],
    [
      0.132117,
      "i"
    ],
    [
      0.119444,
      "r"
    ],
    [
      0.235772,
      "n"
    ],
    [
      0.079939,
      "a"
    ],
    [
      0.125264,
      "m"
    ],
    [
      0.126023,
      "e"
    ],
    [
      0.628355,
      "\r\n[laks@ webminal.org]$ "
    ],
    [
      0.952044,
      "d"
    ],
    [
      0.149462,
      "i"
    ],
    [
      0.112881,
      "r"
    ],
    [
      0.301955,
      "n"
    ],
    [
      0.118610,
      "a"
    ],
    [
      0.130078,
      "m"
    ],
    [
      0.120618,
      "e"
    ],
    [
      0.113544,
      " "
    ],
    [
      0.252522,
      "/"
    ],
    [
      0.253611,
      "h"
    ],
    [
      0.117772,
      "o"
    ],
    [
      0.079702,
      "m"
    ],
    [
      0.122749,
      "e"
    ],
    [
      0.213083,
      "/"
    ],
    [
      0.253475,
      "l"
    ],
    [
      0.089568,
      "a"
    ],
    [
      0.134166,
      "k"
    ],
    [
      0.071816,
      "s"
    ],
    [
      0.198678,
      "/"
    ],
    [
      0.801995,
      "s"
    ],
    [
      0.140884,
      "o"
    ],
    [
      0.094017,
      "m"
    ],
    [
      0.098671,
      "e"
    ],
    [
      0.277191,
      "/"
    ],
    [
      0.163772,
      "d"
    ],
    [
      0.164159,
      "i"
    ],
    [
      0.133394,
      "r"
    ],
    [
      0.325450,
      "/"
    ],
    [
      0.289789,
      "f"
    ],
    [
      0.155121,
      "i"
    ],
    [
      0.074530,
      "l"
    ],
    [
      0.122411,
      "e"
    ],
    [
      0.175322,
      "."
    ],
    [
      0.102694,
      "e"
    ],
    [
      0.572221,
      "\u0008\u001b[K"
    ],
    [
      0.157157,
      "t"
    ],
    [
      0.267204,
      "x"
    ],
    [
      0.236071,
      "t"
    ],
    [
      0.479902,
      "\r\n"
    ],
    [
      0.001939,
      "/home/laks/some/dir\r\n"
    ],
    [
      0.001130,
      "[laks@ webminal.org]$ "
    ],
    [
      1.321197,
      "#"
    ],
    [
      0.141482,
      " "
    ],
    [
      2.419552,
      "y"
    ],
    [
      0.282927,
      "e"
    ],
    [
      0.472455,
      "s"
    ],
    [
      0.339559,
      ","
    ],
    [
      0.116629,
      " "
    ],
    [
      0.119141,
      "w"
    ],
    [
      0.127623,
      "e"
    ],
    [
      0.098335,
      " "
    ],
    [
      0.880942,
      "g"
    ],
    [
      0.084999,
      "o"
    ],
    [
      0.191515,
      "t"
    ],
    [
      0.084340,
      " "
    ],
    [
      0.099967,
      "t"
    ],
    [
      0.114789,
      "h"
    ],
    [
      0.105310,
      "e"
    ],
    [
      0.177692,
      "m"
    ],
    [
      0.540728,
      "!"
    ],
    [
      0.154777,
      " "
    ],
    [
      2.060429,
      "\r\n[laks@ webminal.org]$ "
    ],
    [
      1.681946,
      "e"
    ],
    [
      0.249135,
      "x"
    ],
    [
      0.186919,
      "i"
    ],
    [
      0.197281,
      "t"
    ],
    [
      0.287711,
      "\r\nexit\r\n"
    ]
  ]
}